owl_model_extractor/__init__.py
owl_model_extractor/owl_model.py
owl_model_extractor/owl_model_extractor_constants_values.py
owl_model_extractor-0.2.8.dist-info/METADATA
owl_model_extractor-0.2.8.dist-info/WHEEL
owl_model_extractor-0.2.8.dist-info/top_level.txt
owl_model_extractor-0.2.8.dist-info/RECORD
