Metadata-Version: 2.1
Name: owl-model-extractor
Version: 0.2.8
Summary: Librería que nos permite acceder a un fichero OWL tanto local como remoto y modelar la información que contiene
Home-page: 
Author: KnowledgeFactory
Maintainer: KnowledgeFactory
License: MIT
Keywords: kfsembu,knowledge-factory,helpers,utils,utilities,useful-methods
Requires-Python: >=3.6
Requires-Dist: Owlready2 (==0.39)
Requires-Dist: rdflib (==6.1.1)
